<?xml version="1.0" ?>
<annotation>
<folder>Tianchi</folder>
<filename>aug_9_corn08.jpg</filename>
<source>
<database>The Tianchi Database</database>
<annotation>Tianchi</annotation>
</source>
<size>
<width>500</width>
<height>500</height>
<depth>3</depth>
</size>
<object>
<name>corn</name>
<pose>Unspecified</pose>
<truncated>1</truncated>
<difficult>0</difficult>
<bndbox>
<xmin>120</xmin>
<ymin>49</ymin>
<xmax>240</xmax>
<ymax>450</ymax>
</bndbox>
</object>
<object>
<name>corn</name>
<pose>Unspecified</pose>
<truncated>1</truncated>
<difficult>0</difficult>
<bndbox>
<xmin>225</xmin>
<ymin>73</ymin>
<xmax>340</xmax>
<ymax>462</ymax>
</bndbox>
</object>
</annotation>
