<?xml version="1.0" ?>
<annotation>
<folder>Tianchi</folder>
<filename>aug_6_corn05.jpg</filename>
<source>
<database>The Tianchi Database</database>
<annotation>Tianchi</annotation>
</source>
<size>
<width>266</width>
<height>160</height>
<depth>3</depth>
</size>
<object>
<name>corn</name>
<pose>Unspecified</pose>
<truncated>1</truncated>
<difficult>0</difficult>
<bndbox>
<xmin>24</xmin>
<ymin>78</ymin>
<xmax>241</xmax>
<ymax>142</ymax>
</bndbox>
</object>
<object>
<name>corn</name>
<pose>Unspecified</pose>
<truncated>1</truncated>
<difficult>0</difficult>
<bndbox>
<xmin>43</xmin>
<ymin>37</ymin>
<xmax>215</xmax>
<ymax>89</ymax>
</bndbox>
</object>
<object>
<name>corn</name>
<pose>Unspecified</pose>
<truncated>1</truncated>
<difficult>0</difficult>
<bndbox>
<xmin>49</xmin>
<ymin>10</ymin>
<xmax>196</xmax>
<ymax>63</ymax>
</bndbox>
</object>
</annotation>
