<?xml version="1.0" ?>
<annotation>
<folder>Tianchi</folder>
<filename>aug_4_wheat16.jpg</filename>
<source>
<database>The Tianchi Database</database>
<annotation>Tianchi</annotation>
</source>
<size>
<width>780</width>
<height>566</height>
<depth>3</depth>
</size>
<object>
<name>wheat</name>
<pose>Unspecified</pose>
<truncated>1</truncated>
<difficult>0</difficult>
<bndbox>
<xmin>153</xmin>
<ymin>57</ymin>
<xmax>397</xmax>
<ymax>342</ymax>
</bndbox>
</object>
<object>
<name>wheat</name>
<pose>Unspecified</pose>
<truncated>1</truncated>
<difficult>0</difficult>
<bndbox>
<xmin>376</xmin>
<ymin>71</ymin>
<xmax>745</xmax>
<ymax>257</ymax>
</bndbox>
</object>
<object>
<name>wheat</name>
<pose>Unspecified</pose>
<truncated>1</truncated>
<difficult>0</difficult>
<bndbox>
<xmin>346</xmin>
<ymin>258</ymin>
<xmax>681</xmax>
<ymax>453</ymax>
</bndbox>
</object>
</annotation>
