<?xml version="1.0" ?>
<annotation>
<folder>Tianchi</folder>
<filename>aug_9_rice14.jpg</filename>
<source>
<database>The Tianchi Database</database>
<annotation>Tianchi</annotation>
</source>
<size>
<width>487</width>
<height>566</height>
<depth>3</depth>
</size>
<object>
<name>rice</name>
<pose>Unspecified</pose>
<truncated>1</truncated>
<difficult>0</difficult>
<bndbox>
<xmin>96</xmin>
<ymin>285</ymin>
<xmax>375</xmax>
<ymax>511</ymax>
</bndbox>
</object>
<object>
<name>rice</name>
<pose>Unspecified</pose>
<truncated>1</truncated>
<difficult>0</difficult>
<bndbox>
<xmin>125</xmin>
<ymin>173</ymin>
<xmax>472</xmax>
<ymax>502</ymax>
</bndbox>
</object>
</annotation>
